chinaarea/__init__.py
chinaarea/chinaarea.py
chinaarea/stats_spider/__init__.py
chinaarea/stats_spider/china_area.sqlite
chinaarea/stats_spider/items.py
chinaarea/stats_spider/middlewares.py
chinaarea/stats_spider/models.py
chinaarea/stats_spider/pipelines.py
chinaarea/stats_spider/settings.py
chinaarea/stats_spider/spiders/__init__.py
chinaarea/stats_spider/spiders/area_spider.py
chinaarea-0.0.5.dist-info/DESCRIPTION.rst
chinaarea-0.0.5.dist-info/METADATA
chinaarea-0.0.5.dist-info/RECORD
chinaarea-0.0.5.dist-info/WHEEL
chinaarea-0.0.5.dist-info/metadata.json
chinaarea-0.0.5.dist-info/top_level.txt
