Metadata-Version: 2.0
Name: chinaarea
Version: 0.0.5
Summary: get a china area by province, city or county
Home-page: https://github.com/mouday/chinaarea
Author: Peng Shiyu
Author-email: pengshiyuyx@gmail.com
License: MIT License
Platform: UNKNOWN
Classifier: Programming Language :: Python :: 3
Classifier: License :: OSI Approved :: MIT License
Classifier: Operating System :: OS Independent
Requires-Dist: peewee (==3.3.4)
Requires-Dist: jieba (==0.39)
